[{"timestamp": 0.043, "opening_sensor": false, "presence_control_sensor": false, "closing_sensor": false}, {"timestamp": 0.093, "opening_sensor": false, "presence_control_sensor": false, "closing_sensor": false}, {"timestamp": 0.143, "opening_sensor": false, "presence_control_sensor": false, "closing_sensor": false}, {"timestamp": 0.192, "opening_sensor": false, "presence_control_sensor": false, "closing_sensor": false}, {"timestamp": 0.242, "opening_sensor": false, "presence_control_sensor": false, "closing_sensor": false}, {"timestamp": 0.292, "opening_sensor": false, "presence_control_sensor": false, "closing_sensor": false}, {"timestamp": 0.342, "opening_sensor": false, "presence_control_sensor": false, "closing_sensor": false}, {"timestamp": 0.392, "opening_sensor": false, "presence_control_sensor": false, "closing_sensor": false}, {"timestamp": 0.446, "opening_sensor": false, "presence_control_sensor": false, "closing_sensor": false}, {"timestamp": 0.492, "opening_sensor": false, "presence_control_sensor": false, "closing_sensor": false}, {"timestamp": 0.542, "opening_sensor": false, "presence_control_sensor": false, "closing_sensor": false}, {"timestamp": 0.592, "opening_sensor": false, "presence_control_sensor": false, "closing_sensor": false}, {"timestamp": 0.642, "opening_sensor": false, "presence_control_sensor": false, "closing_sensor": false}, {"timestamp": 0.693, "opening_sensor": false, "presence_control_sensor": false, "closing_sensor": false}, {"timestamp": 0.742, "opening_sensor": true, "presence_control_sensor": false, "closing_sensor": false}, {"timestamp": 0.793, "opening_sensor": true, "presence_control_sensor": false, "closing_sensor": false}, {"timestamp": 0.87, "opening_sensor": true, "presence_control_sensor": false, "closing_sensor": false}, {"timestamp": 0.892, "opening_sensor": true, "presence_control_sensor": false, "closing_sensor": false}, {"timestamp": 0.943, "opening_sensor": true, "presence_control_sensor": true, "closing_sensor": false}, {"timestamp": 0.992, "opening_sensor": true, "presence_control_sensor": true, "closing_sensor": false}, {"timestamp": 1.042, "opening_sensor": true, "presence_control_sensor": true, "closing_sensor": false}, {"timestamp": 1.092, "opening_sensor": true, "presence_control_sensor": true, "closing_sensor": true}, {"timestamp": 1.142, "opening_sensor": false, "presence_control_sensor": true, "closing_sensor": true}, {"timestamp": 1.192, "opening_sensor": false, "presence_control_sensor": true, "closing_sensor": true}, {"timestamp": 1.242, "opening_sensor": false, "presence_control_sensor": true, "closing_sensor": true}, {"timestamp": 1.298, "opening_sensor": false, "presence_control_sensor": true, "closing_sensor": true}, {"timestamp": 1.342, "opening_sensor": false, "presence_control_sensor": false, "closing_sensor": true}, {"timestamp": 1.393, "opening_sensor": false, "presence_control_sensor": false, "closing_sensor": true}, {"timestamp": 1.443, "opening_sensor": false, "presence_control_sensor": false, "closing_sensor": true}, {"timestamp": 1.493, "opening_sensor": false, "presence_control_sensor": false, "closing_sensor": false}, {"timestamp": 1.542, "opening_sensor": false, "presence_control_sensor": false, "closing_sensor": false}, {"timestamp": 1.592, "opening_sensor": false, "presence_control_sensor": false, "closing_sensor": false}, {"timestamp": 1.642, "opening_sensor": false, "presence_control_sensor": false, "closing_sensor": false}, {"timestamp": 1.72, "opening_sensor": false, "presence_control_sensor": false, "closing_sensor": false}, {"timestamp": 1.742, "opening_sensor": false, "presence_control_sensor": false, "closing_sensor": false}, {"timestamp": 1.789, "opening_sensor": false, "presence_control_sensor": false, "closing_sensor": false}, {"timestamp": 1.842, "opening_sensor": false, "presence_control_sensor": false, "closing_sensor": false}, {"timestamp": 1.892, "opening_sensor": false, "presence_control_sensor": false, "closing_sensor": false}, {"timestamp": 1.942, "opening_sensor": false, "presence_control_sensor": false, "closing_sensor": false}, {"timestamp": 1.992, "opening_sensor": false, "presence_control_sensor": false, "closing_sensor": false}, {"timestamp": 2.042, "opening_sensor": false, "presence_control_sensor": false, "closing_sensor": false}, {"timestamp": 2.092, "opening_sensor": false, "presence_control_sensor": false, "closing_sensor": false}, {"timestamp": 2.143, "opening_sensor": false, "presence_control_sensor": false, "closing_sensor": false}, {"timestamp": 2.193, "opening_sensor": false, "presence_control_sensor": false, "closing_sensor": false}, {"timestamp": 2.242, "opening_sensor": false, "presence_control_sensor": false, "closing_sensor": false}, {"timestamp": 2.293, "opening_sensor": false, "presence_control_sensor": false, "closing_sensor": false}, {"timestamp": 2.342, "opening_sensor": false, "presence_control_sensor": false, "closing_sensor": false}, {"timestamp": 2.393, "opening_sensor": false, "presence_control_sensor": false, "closing_sensor": false}, {"timestamp": 2.442, "opening_sensor": false, "presence_control_sensor": false, "closing_sensor": false}, {"timestamp": 2.492, "opening_sensor": false, "presence_control_sensor": false, "closing_sensor": false}, {"timestamp": 2.542, "opening_sensor": false, "presence_control_sensor": false, "closing_sensor": false}, {"timestamp": 2.592, "opening_sensor": false, "presence_control_sensor": false, "closing_sensor": false}, {"timestamp": 2.642, "opening_sensor": false, "presence_control_sensor": false, "closing_sensor": false}, {"timestamp": 2.692, "opening_sensor": false, "presence_control_sensor": false, "closing_sensor": false}]